rotel/__about__.py
rotel/__init__.py
rotel/agent.py
rotel/client.py
rotel/config.py
rotel/error.py
rotel/rotel-agent
rotel-0.0.1a15.dist-info/METADATA
rotel-0.0.1a15.dist-info/WHEEL
rotel-0.0.1a15.dist-info/licenses/LICENSE
rotel-0.0.1a15.dist-info/RECORD
