Metadata-Version: 2.4
Name: rotel
Version: 0.0.1a15
Summary: Lightweight OpenTelemetry collector
Project-URL: Homepage, https://github.com/streamfold/pyrotel
Project-URL: Issues, https://github.com/streamfold/pyrotel/issues
Project-URL: Source, https://github.com/streamfold/pyrotel
Author-email: Ray Jenkins <ray@streamfold.com>, Mike Heffner <mike@streamfold.com>
License-Expression: Apache-2.0
License-File: LICENSE
Classifier: Development Status :: 3 - Alpha
Classifier: Programming Language :: Python
Classifier: Programming Language :: Python :: 3.10
Classifier: Programming Language :: Python :: 3.11
Classifier: Programming Language :: Python :: 3.12
Classifier: Programming Language :: Python :: 3.13
Requires-Python: >=3.10
Requires-Dist: typing-extensions
Provides-Extra: dev
Requires-Dist: pkginfo>=1.12.0; extra == 'dev'
Requires-Dist: pytest>=7.0; extra == 'dev'
Requires-Dist: twine>=6.1.0; extra == 'dev'
